[
  {
    "tsUtc": "2025-10-11T20:57:00Z",
    "temperatureC": 28.92,
    "vibration": 3.12,
    "currentA": 22.61,
    "healthScore": 88.0,
    "failureProb": 0.082,
    "anomaly": 0
  },
  {
    "tsUtc": "2025-10-11T21:07:00Z",
    "temperatureC": 30.78,
    "vibration": 2.23,
    "currentA": 23.06,
    "healthScore": 100.0,
    "failureProb": 0.03,
    "anomaly": 0
  },
  {
    "tsUtc": "2025-10-11T21:17:00Z",
    "temperatureC": 31.25,
    "vibration": 2.39,
    "currentA": 23.7,
    "healthScore": 100.0,
    "failureProb": 0.03,
    "anomaly": 0
  },
  {
    "tsUtc": "2025-10-11T21:27:00Z",
    "temperatureC": 30.79,
    "vibration": 2.94,
    "currentA": 24.38,
    "healthScore": 92.1,
    "failureProb": 0.064,
    "anomaly": 0
  },
  {
    "tsUtc": "2025-10-11T21:37:00Z",
    "temperatureC": 30.83,
    "vibration": 2.79,
    "currentA": 21.0,
    "healthScore": 95.5,
    "failureProb": 0.049,
    "anomaly": 0
  },
  {
    "tsUtc": "2025-10-11T21:47:00Z",
    "temperatureC": 31.32,
    "vibration": 3.32,
    "currentA": 22.88,
    "healthScore": 83.3,
    "failureProb": 0.102,
    "anomaly": 0
  },
  {
    "tsUtc": "2025-10-11T21:57:00Z",
    "temperatureC": 31.23,
    "vibration": 3.16,
    "currentA": 22.9,
    "healthScore": 87.0,
    "failureProb": 0.086,
    "anomaly": 0
  },
  {
    "tsUtc": "2025-10-11T22:07:00Z",
    "temperatureC": 32.93,
    "vibration": 2.34,
    "currentA": 24.74,
    "healthScore": 100.0,
    "failureProb": 0.03,
    "anomaly": 0
  },
  {
    "tsUtc": "2025-10-11T22:17:00Z",
    "temperatureC": 32.91,
    "vibration": 2.82,
    "currentA": 22.71,
    "healthScore": 94.9,
    "failureProb": 0.052,
    "anomaly": 0
  },
  {
    "tsUtc": "2025-10-11T22:27:00Z",
    "temperatureC": 33.82,
    "vibration": 2.69,
    "currentA": 25.31,
    "healthScore": 98.0,
    "failureProb": 0.039,
    "anomaly": 0
  },
  {
    "tsUtc": "2025-10-11T22:37:00Z",
    "temperatureC": 34.34,
    "vibration": 2.65,
    "currentA": 26.79,
    "healthScore": 98.8,
    "failureProb": 0.035,
    "anomaly": 0
  },
  {
    "tsUtc": "2025-10-11T22:47:00Z",
    "temperatureC": 33.01,
    "vibration": 3.11,
    "currentA": 23.91,
    "healthScore": 88.1,
    "failureProb": 0.081,
    "anomaly": 0
  },
  {
    "tsUtc": "2025-10-11T22:57:00Z",
    "temperatureC": 33.11,
    "vibration": 3.2,
    "currentA": 22.52,
    "healthScore": 85.9,
    "failureProb": 0.09,
    "anomaly": 0
  },
  {
    "tsUtc": "2025-10-11T23:07:00Z",
    "temperatureC": 36.18,
    "vibration": 2.24,
    "currentA": 27.71,
    "healthScore": 100.0,
    "failureProb": 0.03,
    "anomaly": 0
  },
  {
    "tsUtc": "2025-10-11T23:17:00Z",
    "temperatureC": 35.3,
    "vibration": 2.86,
    "currentA": 27.51,
    "healthScore": 94.0,
    "failureProb": 0.056,
    "anomaly": 0
  },
  {
    "tsUtc": "2025-10-11T23:27:00Z",
    "temperatureC": 36.37,
    "vibration": 2.87,
    "currentA": 26.37,
    "healthScore": 93.8,
    "failureProb": 0.057,
    "anomaly": 0
  },
  {
    "tsUtc": "2025-10-11T23:37:00Z",
    "temperatureC": 35.45,
    "vibration": 2.9,
    "currentA": 25.47,
    "healthScore": 92.9,
    "failureProb": 0.06,
    "anomaly": 0
  },
  {
    "tsUtc": "2025-10-11T23:47:00Z",
    "temperatureC": 35.61,
    "vibration": 3.19,
    "currentA": 24.53,
    "healthScore": 86.3,
    "failureProb": 0.089,
    "anomaly": 0
  },
  {
    "tsUtc": "2025-10-11T23:57:00Z",
    "temperatureC": 34.49,
    "vibration": 2.8,
    "currentA": 26.96,
    "healthScore": 95.3,
    "failureProb": 0.05,
    "anomaly": 0
  },
  {
    "tsUtc": "2025-10-12T00:07:00Z",
    "temperatureC": 38.19,
    "vibration": 2.62,
    "currentA": 27.61,
    "healthScore": 99.2,
    "failureProb": 0.033,
    "anomaly": 0
  },
  {
    "tsUtc": "2025-10-12T00:17:00Z",
    "temperatureC": 37.11,
    "vibration": 2.95,
    "currentA": 28.71,
    "healthScore": 91.5,
    "failureProb": 0.065,
    "anomaly": 0
  },
  {
    "tsUtc": "2025-10-12T00:27:00Z",
    "temperatureC": 38.6,
    "vibration": 3.0,
    "currentA": 26.82,
    "healthScore": 90.4,
    "failureProb": 0.074,
    "anomaly": 0
  },
  {
    "tsUtc": "2025-10-12T00:37:00Z",
    "temperatureC": 38.19,
    "vibration": 3.06,
    "currentA": 28.17,
    "healthScore": 89.1,
    "failureProb": 0.078,
    "anomaly": 0
  },
  {
    "tsUtc": "2025-10-12T00:47:00Z",
    "temperatureC": 37.47,
    "vibration": 2.9,
    "currentA": 28.35,
    "healthScore": 92.9,
    "failureProb": 0.06,
    "anomaly": 0
  },
  {
    "tsUtc": "2025-10-12T00:57:00Z",
    "temperatureC": 38.39,
    "vibration": 2.93,
    "currentA": 29.73,
    "healthScore": 90.1,
    "failureProb": 0.066,
    "anomaly": 0
  },
  {
    "tsUtc": "2025-10-12T01:07:00Z",
    "temperatureC": 39.61,
    "vibration": 2.82,
    "currentA": 30.56,
    "healthScore": 88.3,
    "failureProb": 0.062,
    "anomaly": 0
  },
  {
    "tsUtc": "2025-10-12T01:17:00Z",
    "temperatureC": 40.23,
    "vibration": 2.87,
    "currentA": 29.76,
    "healthScore": 88.2,
    "failureProb": 0.071,
    "anomaly": 0
  },
  {
    "tsUtc": "2025-10-12T01:27:00Z",
    "temperatureC": 39.71,
    "vibration": 3.14,
    "currentA": 28.9,
    "healthScore": 85.8,
    "failureProb": 0.094,
    "anomaly": 0
  },
  {
    "tsUtc": "2025-10-12T01:37:00Z",
    "temperatureC": 39.74,
    "vibration": 2.69,
    "currentA": 30.89,
    "healthScore": 88.0,
    "failureProb": 0.05,
    "anomaly": 0
  },
  {
    "tsUtc": "2025-10-12T01:47:00Z",
    "temperatureC": 39.59,
    "vibration": 2.82,
    "currentA": 29.76,
    "healthScore": 90.3,
    "failureProb": 0.061,
    "anomaly": 0
  },
  {
    "tsUtc": "2025-10-12T01:57:00Z",
    "temperatureC": 40.12,
    "vibration": 2.82,
    "currentA": 28.5,
    "healthScore": 90.9,
    "failureProb": 0.065,
    "anomaly": 0
  },
  {
    "tsUtc": "2025-10-12T02:07:00Z",
    "temperatureC": 43.34,
    "vibration": 2.82,
    "currentA": 32.63,
    "healthScore": 74.7,
    "failureProb": 0.086,
    "anomaly": 0
  },
  {
    "tsUtc": "2025-10-12T02:17:00Z",
    "temperatureC": 43.74,
    "vibration": 3.12,
    "currentA": 31.98,
    "healthScore": 72.7,
    "failureProb": 0.118,
    "anomaly": 0
  },
  {
    "tsUtc": "2025-10-12T02:27:00Z",
    "temperatureC": 42.24,
    "vibration": 2.92,
    "currentA": 32.19,
    "healthScore": 77.9,
    "failureProb": 0.088,
    "anomaly": 0
  },
  {
    "tsUtc": "2025-10-12T02:37:00Z",
    "temperatureC": 42.94,
    "vibration": 2.59,
    "currentA": 31.58,
    "healthScore": 78.6,
    "failureProb": 0.061,
    "anomaly": 0
  },
  {
    "tsUtc": "2025-10-12T02:47:00Z",
    "temperatureC": 42.49,
    "vibration": 2.85,
    "currentA": 31.76,
    "healthScore": 78.7,
    "failureProb": 0.083,
    "anomaly": 0
  },
  {
    "tsUtc": "2025-10-12T02:57:00Z",
    "temperatureC": 42.67,
    "vibration": 2.55,
    "currentA": 29.95,
    "healthScore": 82.3,
    "failureProb": 0.059,
    "anomaly": 0
  },
  {
    "tsUtc": "2025-10-12T03:07:00Z",
    "temperatureC": 43.76,
    "vibration": 2.82,
    "currentA": 31.96,
    "healthScore": 75.0,
    "failureProb": 0.088,
    "anomaly": 0
  },
  {
    "tsUtc": "2025-10-12T03:17:00Z",
    "temperatureC": 43.55,
    "vibration": 3.22,
    "currentA": 30.95,
    "healthScore": 73.7,
    "failureProb": 0.126,
    "anomaly": 0
  },
  {
    "tsUtc": "2025-10-12T03:27:00Z",
    "temperatureC": 44.07,
    "vibration": 2.89,
    "currentA": 32.45,
    "healthScore": 72.8,
    "failureProb": 0.097,
    "anomaly": 0
  },
  {
    "tsUtc": "2025-10-12T03:37:00Z",
    "temperatureC": 44.55,
    "vibration": 3.19,
    "currentA": 31.47,
    "healthScore": 70.6,
    "failureProb": 0.13,
    "anomaly": 0
  },
  {
    "tsUtc": "2025-10-12T03:47:00Z",
    "temperatureC": 45.36,
    "vibration": 2.82,
    "currentA": 32.64,
    "healthScore": 69.1,
    "failureProb": 0.098,
    "anomaly": 0
  },
  {
    "tsUtc": "2025-10-12T03:57:00Z",
    "temperatureC": 43.96,
    "vibration": 2.92,
    "currentA": 34.49,
    "healthScore": 68.3,
    "failureProb": 0.099,
    "anomaly": 0
  },
  {
    "tsUtc": "2025-10-12T04:07:00Z",
    "temperatureC": 46.56,
    "vibration": 3.03,
    "currentA": 35.12,
    "healthScore": 59.8,
    "failureProb": 0.126,
    "anomaly": 0
  },
  {
    "tsUtc": "2025-10-12T04:17:00Z",
    "temperatureC": 45.91,
    "vibration": 2.82,
    "currentA": 32.49,
    "healthScore": 67.8,
    "failureProb": 0.101,
    "anomaly": 0
  },
  {
    "tsUtc": "2025-10-12T04:27:00Z",
    "temperatureC": 45.62,
    "vibration": 2.86,
    "currentA": 33.51,
    "healthScore": 66.5,
    "failureProb": 0.104,
    "anomaly": 0
  },
  {
    "tsUtc": "2025-10-12T04:37:00Z",
    "temperatureC": 46.61,
    "vibration": 2.84,
    "currentA": 33.12,
    "healthScore": 64.5,
    "failureProb": 0.108,
    "anomaly": 0
  },
  {
    "tsUtc": "2025-10-12T04:47:00Z",
    "temperatureC": 47.1,
    "vibration": 2.69,
    "currentA": 34.52,
    "healthScore": 60.8,
    "failureProb": 0.096,
    "anomaly": 0
  },
  {
    "tsUtc": "2025-10-12T04:57:00Z",
    "temperatureC": 45.98,
    "vibration": 2.46,
    "currentA": 34.61,
    "healthScore": 63.7,
    "failureProb": 0.08,
    "anomaly": 0
  },
  {
    "tsUtc": "2025-10-12T05:07:00Z",
    "temperatureC": 47.12,
    "vibration": 3.1,
    "currentA": 36.24,
    "healthScore": 55.4,
    "failureProb": 0.137,
    "anomaly": 0
  },
  {
    "tsUtc": "2025-10-12T05:17:00Z",
    "temperatureC": 47.95,
    "vibration": 2.97,
    "currentA": 34.99,
    "healthScore": 56.6,
    "failureProb": 0.13,
    "anomaly": 0
  },
  {
    "tsUtc": "2025-10-12T05:27:00Z",
    "temperatureC": 46.89,
    "vibration": 2.86,
    "currentA": 31.99,
    "healthScore": 65.4,
    "failureProb": 0.111,
    "anomaly": 0
  },
  {
    "tsUtc": "2025-10-12T05:37:00Z",
    "temperatureC": 48.26,
    "vibration": 2.69,
    "currentA": 34.4,
    "healthScore": 57.6,
    "failureProb": 0.103,
    "anomaly": 0
  },
  {
    "tsUtc": "2025-10-12T05:47:00Z",
    "temperatureC": 47.5,
    "vibration": 2.48,
    "currentA": 33.9,
    "healthScore": 60.9,
    "failureProb": 0.089,
    "anomaly": 0
  },
  {
    "tsUtc": "2025-10-12T05:57:00Z",
    "temperatureC": 47.69,
    "vibration": 2.47,
    "currentA": 35.31,
    "healthScore": 57.5,
    "failureProb": 0.091,
    "anomaly": 0
  },
  {
    "tsUtc": "2025-10-12T06:07:00Z",
    "temperatureC": 48.16,
    "vibration": 2.84,
    "currentA": 36.03,
    "healthScore": 54.4,
    "failureProb": 0.117,
    "anomaly": 0
  },
  {
    "tsUtc": "2025-10-12T06:17:00Z",
    "temperatureC": 48.42,
    "vibration": 2.75,
    "currentA": 35.29,
    "healthScore": 55.3,
    "failureProb": 0.11,
    "anomaly": 0
  },
  {
    "tsUtc": "2025-10-12T06:27:00Z",
    "temperatureC": 46.47,
    "vibration": 2.55,
    "currentA": 35.24,
    "healthScore": 61.0,
    "failureProb": 0.083,
    "anomaly": 0
  },
  {
    "tsUtc": "2025-10-12T06:37:00Z",
    "temperatureC": 48.15,
    "vibration": 2.46,
    "currentA": 35.02,
    "healthScore": 56.8,
    "failureProb": 0.093,
    "anomaly": 0
  },
  {
    "tsUtc": "2025-10-12T06:47:00Z",
    "temperatureC": 46.69,
    "vibration": 2.31,
    "currentA": 33.26,
    "healthScore": 64.5,
    "failureProb": 0.084,
    "anomaly": 0
  },
  {
    "tsUtc": "2025-10-12T06:57:00Z",
    "temperatureC": 47.83,
    "vibration": 2.26,
    "currentA": 34.4,
    "healthScore": 58.9,
    "failureProb": 0.091,
    "anomaly": 0
  },
  {
    "tsUtc": "2025-10-12T07:07:00Z",
    "temperatureC": 46.53,
    "vibration": 2.87,
    "currentA": 35.8,
    "healthScore": 59.0,
    "failureProb": 0.111,
    "anomaly": 0
  },
  {
    "tsUtc": "2025-10-12T07:17:00Z",
    "temperatureC": 46.61,
    "vibration": 2.75,
    "currentA": 36.41,
    "healthScore": 57.8,
    "failureProb": 0.098,
    "anomaly": 0
  },
  {
    "tsUtc": "2025-10-12T07:27:00Z",
    "temperatureC": 46.81,
    "vibration": 2.84,
    "currentA": 34.6,
    "healthScore": 61.1,
    "failureProb": 0.109,
    "anomaly": 0
  },
  {
    "tsUtc": "2025-10-12T07:37:00Z",
    "temperatureC": 46.87,
    "vibration": 2.66,
    "currentA": 34.29,
    "healthScore": 61.9,
    "failureProb": 0.091,
    "anomaly": 0
  },
  {
    "tsUtc": "2025-10-12T07:47:00Z",
    "temperatureC": 46.41,
    "vibration": 2.28,
    "currentA": 33.87,
    "healthScore": 64.1,
    "failureProb": 0.083,
    "anomaly": 0
  },
  {
    "tsUtc": "2025-10-12T07:57:00Z",
    "temperatureC": 47.29,
    "vibration": 2.23,
    "currentA": 37.04,
    "healthScore": 54.6,
    "failureProb": 0.088,
    "anomaly": 0
  },
  {
    "tsUtc": "2025-10-12T08:07:00Z",
    "temperatureC": 46.61,
    "vibration": 2.84,
    "currentA": 34.47,
    "healthScore": 61.9,
    "failureProb": 0.108,
    "anomaly": 0
  },
  {
    "tsUtc": "2025-10-12T08:17:00Z",
    "temperatureC": 46.63,
    "vibration": 2.81,
    "currentA": 33.31,
    "healthScore": 64.2,
    "failureProb": 0.105,
    "anomaly": 0
  },
  {
    "tsUtc": "2025-10-12T08:27:00Z",
    "temperatureC": 47.5,
    "vibration": 2.28,
    "currentA": 34.01,
    "healthScore": 60.7,
    "failureProb": 0.089,
    "anomaly": 0
  },
  {
    "tsUtc": "2025-10-12T08:37:00Z",
    "temperatureC": 46.58,
    "vibration": 2.26,
    "currentA": 33.64,
    "healthScore": 64.1,
    "failureProb": 0.084,
    "anomaly": 0
  },
  {
    "tsUtc": "2025-10-12T08:47:00Z",
    "temperatureC": 46.83,
    "vibration": 2.25,
    "currentA": 33.71,
    "healthScore": 63.2,
    "failureProb": 0.085,
    "anomaly": 0
  },
  {
    "tsUtc": "2025-10-12T08:57:00Z",
    "temperatureC": 47.46,
    "vibration": 2.18,
    "currentA": 34.36,
    "healthScore": 60.1,
    "failureProb": 0.089,
    "anomaly": 0
  },
  {
    "tsUtc": "2025-10-12T09:07:00Z",
    "temperatureC": 44.88,
    "vibration": 2.68,
    "currentA": 32.42,
    "healthScore": 71.3,
    "failureProb": 0.081,
    "anomaly": 0
  },
  {
    "tsUtc": "2025-10-12T09:17:00Z",
    "temperatureC": 45.0,
    "vibration": 2.38,
    "currentA": 30.24,
    "healthScore": 74.3,
    "failureProb": 0.074,
    "anomaly": 0
  },
  {
    "tsUtc": "2025-10-12T09:27:00Z",
    "temperatureC": 45.84,
    "vibration": 2.55,
    "currentA": 33.4,
    "healthScore": 66.7,
    "failureProb": 0.079,
    "anomaly": 0
  },
  {
    "tsUtc": "2025-10-12T09:37:00Z",
    "temperatureC": 44.1,
    "vibration": 2.19,
    "currentA": 33.92,
    "healthScore": 70.2,
    "failureProb": 0.068,
    "anomaly": 0
  },
  {
    "tsUtc": "2025-10-12T09:47:00Z",
    "temperatureC": 44.9,
    "vibration": 1.98,
    "currentA": 36.42,
    "healthScore": 61.9,
    "failureProb": 0.073,
    "anomaly": 0
  },
  {
    "tsUtc": "2025-10-12T09:57:00Z",
    "temperatureC": 45.23,
    "vibration": 2.13,
    "currentA": 31.86,
    "healthScore": 71.3,
    "failureProb": 0.075,
    "anomaly": 0
  },
  {
    "tsUtc": "2025-10-12T10:07:00Z",
    "temperatureC": 42.88,
    "vibration": 2.63,
    "currentA": 31.28,
    "healthScore": 79.4,
    "failureProb": 0.064,
    "anomaly": 0
  },
  {
    "tsUtc": "2025-10-12T10:17:00Z",
    "temperatureC": 42.09,
    "vibration": 2.41,
    "currentA": 29.6,
    "healthScore": 84.6,
    "failureProb": 0.056,
    "anomaly": 0
  },
  {
    "tsUtc": "2025-10-12T10:27:00Z",
    "temperatureC": 42.84,
    "vibration": 2.1,
    "currentA": 30.63,
    "healthScore": 80.7,
    "failureProb": 0.06,
    "anomaly": 0
  },
  {
    "tsUtc": "2025-10-12T10:37:00Z",
    "temperatureC": 43.07,
    "vibration": 2.31,
    "currentA": 33.14,
    "healthScore": 74.7,
    "failureProb": 0.062,
    "anomaly": 0
  },
  {
    "tsUtc": "2025-10-12T10:47:00Z",
    "temperatureC": 42.96,
    "vibration": 2.42,
    "currentA": 30.13,
    "healthScore": 81.1,
    "failureProb": 0.061,
    "anomaly": 0
  },
  {
    "tsUtc": "2025-10-12T10:57:00Z",
    "temperatureC": 42.05,
    "vibration": 2.39,
    "currentA": 33.02,
    "healthScore": 77.4,
    "failureProb": 0.055,
    "anomaly": 0
  },
  {
    "tsUtc": "2025-10-12T11:07:00Z",
    "temperatureC": 41.07,
    "vibration": 2.56,
    "currentA": 27.55,
    "healthScore": 89.3,
    "failureProb": 0.049,
    "anomaly": 0
  },
  {
    "tsUtc": "2025-10-12T11:17:00Z",
    "temperatureC": 40.61,
    "vibration": 2.57,
    "currentA": 28.31,
    "healthScore": 90.8,
    "failureProb": 0.046,
    "anomaly": 0
  },
  {
    "tsUtc": "2025-10-12T11:27:00Z",
    "temperatureC": 39.38,
    "vibration": 2.33,
    "currentA": 27.99,
    "healthScore": 95.2,
    "failureProb": 0.039,
    "anomaly": 0
  },
  {
    "tsUtc": "2025-10-12T11:37:00Z",
    "temperatureC": 41.3,
    "vibration": 1.97,
    "currentA": 29.99,
    "healthScore": 86.5,
    "failureProb": 0.051,
    "anomaly": 0
  },
  {
    "tsUtc": "2025-10-12T11:47:00Z",
    "temperatureC": 40.86,
    "vibration": 2.28,
    "currentA": 30.62,
    "healthScore": 86.4,
    "failureProb": 0.048,
    "anomaly": 0
  },
  {
    "tsUtc": "2025-10-12T11:57:00Z",
    "temperatureC": 41.08,
    "vibration": 2.14,
    "currentA": 29.12,
    "healthScore": 88.5,
    "failureProb": 0.049,
    "anomaly": 0
  },
  {
    "tsUtc": "2025-10-12T12:07:00Z",
    "temperatureC": 37.79,
    "vibration": 2.47,
    "currentA": 28.95,
    "healthScore": 96.7,
    "failureProb": 0.03,
    "anomaly": 0
  },
  {
    "tsUtc": "2025-10-12T12:17:00Z",
    "temperatureC": 38.74,
    "vibration": 2.35,
    "currentA": 31.04,
    "healthScore": 89.0,
    "failureProb": 0.035,
    "anomaly": 0
  },
  {
    "tsUtc": "2025-10-12T12:27:00Z",
    "temperatureC": 37.6,
    "vibration": 2.29,
    "currentA": 28.07,
    "healthScore": 99.8,
    "failureProb": 0.03,
    "anomaly": 0
  },
  {
    "tsUtc": "2025-10-12T12:37:00Z",
    "temperatureC": 37.75,
    "vibration": 2.14,
    "currentA": 28.08,
    "healthScore": 99.7,
    "failureProb": 0.03,
    "anomaly": 0
  },
  {
    "tsUtc": "2025-10-12T12:47:00Z",
    "temperatureC": 37.55,
    "vibration": 2.42,
    "currentA": 27.27,
    "healthScore": 100.0,
    "failureProb": 0.03,
    "anomaly": 0
  },
  {
    "tsUtc": "2025-10-12T12:57:00Z",
    "temperatureC": 38.55,
    "vibration": 2.19,
    "currentA": 25.89,
    "healthScore": 98.1,
    "failureProb": 0.033,
    "anomaly": 0
  },
  {
    "tsUtc": "2025-10-12T13:07:00Z",
    "temperatureC": 35.26,
    "vibration": 2.22,
    "currentA": 25.44,
    "healthScore": 100.0,
    "failureProb": 0.03,
    "anomaly": 0
  },
  {
    "tsUtc": "2025-10-12T13:17:00Z",
    "temperatureC": 35.59,
    "vibration": 2.0,
    "currentA": 26.35,
    "healthScore": 100.0,
    "failureProb": 0.03,
    "anomaly": 0
  },
  {
    "tsUtc": "2025-10-12T13:27:00Z",
    "temperatureC": 34.35,
    "vibration": 2.28,
    "currentA": 27.77,
    "healthScore": 100.0,
    "failureProb": 0.03,
    "anomaly": 0
  },
  {
    "tsUtc": "2025-10-12T13:37:00Z",
    "temperatureC": 34.85,
    "vibration": 2.16,
    "currentA": 26.66,
    "healthScore": 100.0,
    "failureProb": 0.03,
    "anomaly": 0
  },
  {
    "tsUtc": "2025-10-12T13:47:00Z",
    "temperatureC": 35.62,
    "vibration": 2.33,
    "currentA": 25.35,
    "healthScore": 100.0,
    "failureProb": 0.03,
    "anomaly": 0
  },
  {
    "tsUtc": "2025-10-12T13:57:00Z",
    "temperatureC": 35.63,
    "vibration": 2.22,
    "currentA": 25.98,
    "healthScore": 100.0,
    "failureProb": 0.03,
    "anomaly": 0
  },
  {
    "tsUtc": "2025-10-12T14:07:00Z",
    "temperatureC": 33.17,
    "vibration": 2.4,
    "currentA": 24.6,
    "healthScore": 100.0,
    "failureProb": 0.03,
    "anomaly": 0
  },
  {
    "tsUtc": "2025-10-12T14:17:00Z",
    "temperatureC": 34.13,
    "vibration": 2.22,
    "currentA": 22.85,
    "healthScore": 100.0,
    "failureProb": 0.03,
    "anomaly": 0
  },
  {
    "tsUtc": "2025-10-12T14:27:00Z",
    "temperatureC": 33.9,
    "vibration": 2.44,
    "currentA": 26.43,
    "healthScore": 100.0,
    "failureProb": 0.03,
    "anomaly": 0
  },
  {
    "tsUtc": "2025-10-12T14:37:00Z",
    "temperatureC": 33.65,
    "vibration": 2.24,
    "currentA": 23.68,
    "healthScore": 100.0,
    "failureProb": 0.03,
    "anomaly": 0
  },
  {
    "tsUtc": "2025-10-12T14:47:00Z",
    "temperatureC": 32.43,
    "vibration": 2.34,
    "currentA": 24.66,
    "healthScore": 100.0,
    "failureProb": 0.03,
    "anomaly": 0
  },
  {
    "tsUtc": "2025-10-12T14:57:00Z",
    "temperatureC": 33.46,
    "vibration": 2.36,
    "currentA": 25.43,
    "healthScore": 100.0,
    "failureProb": 0.03,
    "anomaly": 0
  },
  {
    "tsUtc": "2025-10-12T15:07:00Z",
    "temperatureC": 31.59,
    "vibration": 2.38,
    "currentA": 25.24,
    "healthScore": 100.0,
    "failureProb": 0.03,
    "anomaly": 0
  },
  {
    "tsUtc": "2025-10-12T15:17:00Z",
    "temperatureC": 31.23,
    "vibration": 2.3,
    "currentA": 24.04,
    "healthScore": 100.0,
    "failureProb": 0.03,
    "anomaly": 0
  },
  {
    "tsUtc": "2025-10-12T15:27:00Z",
    "temperatureC": 32.13,
    "vibration": 2.48,
    "currentA": 23.04,
    "healthScore": 100.0,
    "failureProb": 0.03,
    "anomaly": 0
  },
  {
    "tsUtc": "2025-10-12T15:37:00Z",
    "temperatureC": 31.31,
    "vibration": 2.33,
    "currentA": 21.48,
    "healthScore": 100.0,
    "failureProb": 0.03,
    "anomaly": 0
  },
  {
    "tsUtc": "2025-10-12T15:47:00Z",
    "temperatureC": 30.44,
    "vibration": 2.44,
    "currentA": 22.39,
    "healthScore": 100.0,
    "failureProb": 0.03,
    "anomaly": 0
  },
  {
    "tsUtc": "2025-10-12T15:57:00Z",
    "temperatureC": 31.85,
    "vibration": 2.38,
    "currentA": 22.61,
    "healthScore": 100.0,
    "failureProb": 0.03,
    "anomaly": 0
  },
  {
    "tsUtc": "2025-10-12T16:07:00Z",
    "temperatureC": 30.92,
    "vibration": 1.92,
    "currentA": 23.93,
    "healthScore": 100.0,
    "failureProb": 0.03,
    "anomaly": 0
  },
  {
    "tsUtc": "2025-10-12T16:17:00Z",
    "temperatureC": 31.63,
    "vibration": 2.32,
    "currentA": 20.85,
    "healthScore": 100.0,
    "failureProb": 0.03,
    "anomaly": 0
  },
  {
    "tsUtc": "2025-10-12T16:27:00Z",
    "temperatureC": 29.01,
    "vibration": 2.53,
    "currentA": 22.05,
    "healthScore": 100.0,
    "failureProb": 0.03,
    "anomaly": 0
  },
  {
    "tsUtc": "2025-10-12T16:37:00Z",
    "temperatureC": 29.96,
    "vibration": 2.62,
    "currentA": 20.25,
    "healthScore": 99.5,
    "failureProb": 0.032,
    "anomaly": 0
  },
  {
    "tsUtc": "2025-10-12T16:47:00Z",
    "temperatureC": 30.01,
    "vibration": 2.55,
    "currentA": 21.82,
    "healthScore": 100.0,
    "failureProb": 0.03,
    "anomaly": 0
  },
  {
    "tsUtc": "2025-10-12T16:57:00Z",
    "temperatureC": 29.63,
    "vibration": 2.64,
    "currentA": 22.09,
    "healthScore": 99.1,
    "failureProb": 0.034,
    "anomaly": 0
  },
  {
    "tsUtc": "2025-10-12T17:07:00Z",
    "temperatureC": 29.88,
    "vibration": 2.57,
    "currentA": 21.49,
    "healthScore": 100.0,
    "failureProb": 0.03,
    "anomaly": 0
  },
  {
    "tsUtc": "2025-10-12T17:17:00Z",
    "temperatureC": 28.34,
    "vibration": 2.23,
    "currentA": 22.2,
    "healthScore": 100.0,
    "failureProb": 0.03,
    "anomaly": 0
  },
  {
    "tsUtc": "2025-10-12T17:27:00Z",
    "temperatureC": 28.76,
    "vibration": 2.65,
    "currentA": 20.89,
    "healthScore": 98.9,
    "failureProb": 0.035,
    "anomaly": 0
  },
  {
    "tsUtc": "2025-10-12T17:37:00Z",
    "temperatureC": 29.39,
    "vibration": 2.58,
    "currentA": 21.82,
    "healthScore": 100.0,
    "failureProb": 0.03,
    "anomaly": 0
  },
  {
    "tsUtc": "2025-10-12T17:47:00Z",
    "temperatureC": 28.02,
    "vibration": 3.17,
    "currentA": 21.32,
    "healthScore": 86.6,
    "failureProb": 0.087,
    "anomaly": 0
  },
  {
    "tsUtc": "2025-10-12T17:57:00Z",
    "temperatureC": 28.71,
    "vibration": 2.92,
    "currentA": 19.1,
    "healthScore": 92.4,
    "failureProb": 0.062,
    "anomaly": 0
  },
  {
    "tsUtc": "2025-10-12T18:07:00Z",
    "temperatureC": 28.48,
    "vibration": 2.5,
    "currentA": 21.35,
    "healthScore": 100.0,
    "failureProb": 0.03,
    "anomaly": 0
  },
  {
    "tsUtc": "2025-10-12T18:17:00Z",
    "temperatureC": 28.03,
    "vibration": 2.18,
    "currentA": 21.97,
    "healthScore": 100.0,
    "failureProb": 0.03,
    "anomaly": 0
  },
  {
    "tsUtc": "2025-10-12T18:27:00Z",
    "temperatureC": 27.73,
    "vibration": 2.48,
    "currentA": 20.21,
    "healthScore": 100.0,
    "failureProb": 0.03,
    "anomaly": 0
  },
  {
    "tsUtc": "2025-10-12T18:37:00Z",
    "temperatureC": 28.02,
    "vibration": 2.58,
    "currentA": 22.23,
    "healthScore": 100.0,
    "failureProb": 0.03,
    "anomaly": 0
  },
  {
    "tsUtc": "2025-10-12T18:47:00Z",
    "temperatureC": 29.08,
    "vibration": 2.82,
    "currentA": 20.93,
    "healthScore": 94.8,
    "failureProb": 0.052,
    "anomaly": 0
  },
  {
    "tsUtc": "2025-10-12T18:57:00Z",
    "temperatureC": 29.37,
    "vibration": 3.1,
    "currentA": 20.79,
    "healthScore": 88.2,
    "failureProb": 0.08,
    "anomaly": 0
  },
  {
    "tsUtc": "2025-10-12T19:07:00Z",
    "temperatureC": 28.83,
    "vibration": 2.07,
    "currentA": 21.31,
    "healthScore": 100.0,
    "failureProb": 0.03,
    "anomaly": 0
  },
  {
    "tsUtc": "2025-10-12T19:17:00Z",
    "temperatureC": 29.2,
    "vibration": 2.34,
    "currentA": 21.3,
    "healthScore": 100.0,
    "failureProb": 0.03,
    "anomaly": 0
  },
  {
    "tsUtc": "2025-10-12T19:27:00Z",
    "temperatureC": 28.45,
    "vibration": 2.81,
    "currentA": 20.39,
    "healthScore": 95.1,
    "failureProb": 0.051,
    "anomaly": 0
  },
  {
    "tsUtc": "2025-10-12T19:37:00Z",
    "temperatureC": 27.38,
    "vibration": 2.53,
    "currentA": 19.86,
    "healthScore": 100.0,
    "failureProb": 0.03,
    "anomaly": 0
  },
  {
    "tsUtc": "2025-10-12T19:47:00Z",
    "temperatureC": 28.53,
    "vibration": 2.84,
    "currentA": 20.94,
    "healthScore": 94.5,
    "failureProb": 0.054,
    "anomaly": 0
  },
  {
    "tsUtc": "2025-10-12T19:57:00Z",
    "temperatureC": 28.82,
    "vibration": 3.14,
    "currentA": 22.07,
    "healthScore": 87.3,
    "failureProb": 0.084,
    "anomaly": 0
  },
  {
    "tsUtc": "2025-10-12T20:07:00Z",
    "temperatureC": 29.14,
    "vibration": 2.34,
    "currentA": 20.63,
    "healthScore": 100.0,
    "failureProb": 0.03,
    "anomaly": 0
  },
  {
    "tsUtc": "2025-10-12T20:17:00Z",
    "temperatureC": 30.44,
    "vibration": 2.89,
    "currentA": 20.61,
    "healthScore": 93.2,
    "failureProb": 0.059,
    "anomaly": 0
  },
  {
    "tsUtc": "2025-10-12T20:27:00Z",
    "temperatureC": 30.32,
    "vibration": 2.64,
    "currentA": 22.18,
    "healthScore": 99.1,
    "failureProb": 0.034,
    "anomaly": 0
  },
  {
    "tsUtc": "2025-10-12T20:37:00Z",
    "temperatureC": 29.13,
    "vibration": 2.8,
    "currentA": 21.84,
    "healthScore": 95.2,
    "failureProb": 0.05,
    "anomaly": 0
  },
  {
    "tsUtc": "2025-10-12T20:47:00Z",
    "temperatureC": 30.25,
    "vibration": 3.11,
    "currentA": 21.32,
    "healthScore": 88.0,
    "failureProb": 0.081,
    "anomaly": 0
  },
  {
    "tsUtc": "2025-10-12T20:57:00Z",
    "temperatureC": 29.39,
    "vibration": 3.14,
    "currentA": 21.93,
    "healthScore": 87.5,
    "failureProb": 0.084,
    "anomaly": 0
  }
]
